{"pageContext":{"team":{"address":null,"city":"San Jose","country":"USA","gmaps_place_id":null,"gmaps_url":null,"home_championship":{"2017":"Houston","2018":"Houston"},"key":"frc668","lat":null,"lng":null,"location_name":null,"motto":"Inspired by Necessity, created by Genius, forged by Teamwork","name":"Gilbert-Greenstein Family/KLA-Tencor Foundation/Google/Boston Scientific/BAE/Brin Wojcicki Foundation/Solidworks/Xilinx&Pioneer High&Family/Community","nickname":"The Apes of Wrath","postal_code":"95118","rookie_year":2001,"state_prov":"California","team_number":668,"website":"http://www.apesofwrath668.org"}}}